apicheck_package_manager/__init__.py
apicheck_package_manager/__main__.py
apicheck_package_manager-0.0.16.dist-info/METADATA
apicheck_package_manager-0.0.16.dist-info/WHEEL
apicheck_package_manager-0.0.16.dist-info/entry_points.txt
apicheck_package_manager-0.0.16.dist-info/top_level.txt
apicheck_package_manager-0.0.16.dist-info/RECORD
