Metadata-Version: 2.1
Name: apicheck-package-manager
Version: 0.0.16
Summary: APICheck package manager
Home-page: https://github.com/BBVA/apicheck
Author: UNKNOWN
Author-email: UNKNOWN
License: License :: OSI Approved :: Apache Software License
Keywords: apicheck,manager,security
Platform: UNKNOWN
Classifier: Programming Language :: Python :: 3.5
Classifier: Programming Language :: Python :: 3.6
Classifier: Programming Language :: Python :: 3.7
Classifier: Programming Language :: Python :: Implementation :: PyPy
